vessqc/__init__.py
vessqc/_widget.py
vessqc/napari.yaml
vessqc/_tests/__init__.py
vessqc/_tests/test_widget.py
vessqc-0.8.0.dist-info/licenses/LICENSE
vessqc-0.8.0.dist-info/METADATA
vessqc-0.8.0.dist-info/WHEEL
vessqc-0.8.0.dist-info/entry_points.txt
vessqc-0.8.0.dist-info/top_level.txt
vessqc-0.8.0.dist-info/RECORD
