Metadata-Version: 2.4
Name: VessQC
Version: 0.8.0
Summary: Quality control plugin for vessel segmentation in napari
Author-email: Peter Lampen <lampen@isas.de>
License: 
Project-URL: Homepage, https://github.com/MMV-Lab/VessQC
Project-URL: Bug Tracker, https://github.com/MMV-Lab/VessQC/issues
Project-URL: Documentation, https://github.com/MMV-Lab/VessQC#README.md
Project-URL: Source Code, https://github.com/MMV-Lab/VessQC
Project-URL: User Support, https://github.com/MMV-Lab/VessQC/issues
Classifier: Development Status :: 3 - Alpha
Classifier: Intended Audience :: Science/Research
Classifier: Framework :: napari
Classifier: Topic :: Scientific/Engineering :: Image Processing
Classifier: Programming Language :: Python
Classifier: Programming Language :: Python :: 3
Classifier: Programming Language :: Python :: 3.9
Classifier: Programming Language :: Python :: 3.10
Classifier: Programming Language :: Python :: 3.11
Classifier: Programming Language :: Python :: 3.12
Classifier: Operating System :: OS Independent
Classifier: License :: OSI Approved :: BSD License
Requires-Python: >=3.9
License-File: LICENSE
Requires-Dist: joblib>=1.2
Requires-Dist: napari>=0.4.18
Requires-Dist: numpy>=1.23
Requires-Dist: qtpy>=2.3
Requires-Dist: scipy>=1.9
Requires-Dist: SimpleITK>=2.2
Requires-Dist: tifffile>=2023.2.28
Provides-Extra: qt
Requires-Dist: pyqt5; extra == "qt"
Provides-Extra: testing
Requires-Dist: tox; extra == "testing"
Requires-Dist: pytest; extra == "testing"
Requires-Dist: pytest-cov; extra == "testing"
Requires-Dist: pytest-qt; extra == "testing"
Dynamic: license-file
